{
  "subtitle": "Games, Art, and Giving on Monad",
  "description": "Play memory games, create art, and support causes with donations. All in one joyful mini app on Monad.",
  "ogTitle": "Fun & Fund",
  "ogDescription": "A joyful experience: play games, create art, and make a difference with donations.",
  "ogImageUrl": "https://chrismini.netlify.app/images/feed.png",
  "tagline": "Play. Create. Give.",
  "heroImageUrl": "https://chrismini.netlify.app/images/feed.png",
  "accountAssociation": {
    "header": "eyJmaWQiOjI2NTAwOCwidHlwZSI6ImN1c3RvZHkiLCJrZXkiOiIweGUwOGRkODY5MzU1ZDUyMjE0NDg5M2RiNkFkQ2Y2ZDU3NzdFZTQ2OTgifQ",
    "payload": "eyJkb21haW4iOiJjaHJpc21pbmkubmV0bGlmeS5hcHAifQ",
    "signature": "MHg1YTdkZDhmMjQyZWExNDA2OGY2ZjJkM2M0NGJjOTA5ZTgxODcxZGE4YzNhMWVjZGVkZGI5OGZiMTMxMTAyMTY2Nzg1ZjhhYmRlZGJjOGEzOTRiN2FhMTNiMWU1MDllMjBlZDExNmRiNjkzYmQ2OTQ4MTg1MDM4NGMzYzBhY2ViODFj"
  },
  "frame": {
    "version": "1",
    "name": "Fun & Fund",
    "iconUrl": "https://chrismini.netlify.app/images/icon.jpeg",
    "homeUrl": "https://chrismini.netlify.app",
    "imageUrl": "https://chrismini.netlify.app/images/feed.png",
    "screenshotUrls": [],
    "tags": ["monad", "farcaster", "miniapp", "games", "art"],
    "primaryCategory": "games",
    "buttonTitle": "Fun & Fund",
    "splashImageUrl": "https://chrismini.netlify.app/images/splash.jpeg",
    "splashBackgroundColor": "#ffffff",
    "webhookUrl": "https://chrismini.netlify.app/api/webhook"
  }
} 